MANIFEST.in
README.rst
setup.cfg
setup.py
floo/floo.py
floo/floo_test.py
floo.egg-info/PKG-INFO
floo.egg-info/SOURCES.txt
floo.egg-info/dependency_links.txt
floo.egg-info/top_level.txt