Metadata-Version: 1.1
Name: floo
Version: 0.1.2
Summary: A small library to get order and basic operations for an arbitrary set of symbols.
Home-page: https://github.com/jkklapp/floo
Author: Jaakko Lappalainen
Author-email: jkk.lapp@gmail.com
License: Apache License
Download-URL: https://github.com/jkklapp/floo/tarball/dist
Keywords: order,n-ary,arithmetic
Platform: UNKNOWN
